Workbook
Name dividendos: Planilha1!$D$21
Name investimento_inicial: Planilha1!$D$17
Name periodo: Planilha1!$D$18
Name período: Planilha1!$D$18
Name rendimento_carteira: Planilha1!$D$13

Sheet Planilha1
B11: CONFIGURAÇÕES
B12: Salário | D12: 4200
B13: Rendimento Carteira | D13: 0.006
B14: Sugestão de invesntimento | D14: =D12*30% -> 1260
B16: INVESTIMENTO MENSAL
B17: Quanto investir por mês? | D17: 200
B18: Por quantos anos? | D18: 5
B19: Taxa de rendimento anual? | D19: 0.01079
B20: Quanto de patrimônio acumulado? | D20: =FV(D19,D18*12,D17)*(-1) -> 16755.383
B21: Dividendos mensais? | D21: =D20*D13 -> 100.5323
B23: Cenários | D23: Dividendos
A24: 2 | B24: Quanto em 2 Anos | C24: =FV($D$19,$A24*12,$D$17)*(-1) -> 5445.5255 | D24: =C24*rendimento_carteira -> 32.673153
A25: 5 | B25: Quanto em 5 Anos | C25: =FV($D$19,$A25*12,$D$17)*(-1) -> 16755.383 | D25: =C25*rendimento_carteira -> 100.5323
A26: 10 | B26: Quanto em 10 Anos | C26: =FV($D$19,$A26*12,$D$17)*(-1) -> 48656.843 | D26: =C26*rendimento_carteira -> 291.94106
A27: 20 | B27: Quanto em 20 Anos | C27: =FV($D$19,$A27*12,$D$17)*(-1) -> 225039.68 | D27: =C27*rendimento_carteira -> 1350.2381
A28: 30 | B28: Quanto em 30 Anos | C28: =FV($D$19,$A28*12,$D$17)*(-1) -> 864433.93 | D28: =C28*rendimento_carteira -> 5186.6036
B31: PERFIL | C31: AGRESSIVO
B32: valor a ser investido por mês | C32: =investimento_inicial -> 200
B34: TIPO DE FIL | C34: PERCENTUAL SUGERIDO | D34: VALORES
A35: =$C$31&"-"&B35 -> AGRESSIVO-PAPEL | B35: PAPEL | C35: =VLOOKUP(A35,Planilha2!A:D,4,FALSE) -> 0.5 | D35: =VLOOKUP(A35,Planilha2!A:D,4,0)*$C$32 -> 100
A36: =$C$31&"-"&B36 -> AGRESSIVO-TIJOLO | B36: TIJOLO | C36: =VLOOKUP(A36,Planilha2!A:D,4,FALSE) -> 0.1 | D36: =VLOOKUP(A36,Planilha2!A:D,4,0)*$C$32 -> 20
A37: =$C$31&"-"&B37 -> AGRESSIVO-HIBRIDOS | B37: HIBRIDOS | C37: =VLOOKUP(A37,Planilha2!A:D,4,FALSE) -> 0.05 | D37: =VLOOKUP(A37,Planilha2!A:D,4,0)*$C$32 -> 10
A38: =$C$31&"-"&B38 -> AGRESSIVO-FOPS | B38: FOPS | C38: =VLOOKUP(A38,Planilha2!A:D,4,FALSE) -> 0.05 | D38: =VLOOKUP(A38,Planilha2!A:D,4,0)*$C$32 -> 10
A39: =$C$31&"-"&B39 -> AGRESSIVO-DESENVOLVIMENTO | B39: DESENVOLVIMENTO | C39: =VLOOKUP(A39,Planilha2!A:D,4,FALSE) -> 0.2 | D39: =VLOOKUP(A39,Planilha2!A:D,4,0)*$C$32 -> 40
A40: =$C$31&"-"&B40 -> AGRESSIVO-HOTELARIAS | B40: HOTELARIAS | C40: =VLOOKUP(A40,Planilha2!A:D,4,FALSE) -> 0.1 | D40: =VLOOKUP(A40,Planilha2!A:D,4,0)*$C$32 -> 20
D41: =SUM(D35:D40) -> 200

Sheet Planilha2
A2: CHAVE | B2: PERFIL | C2: TIPO DE FIL | D2: %
A3: CONSERVADOR-PAPEL | B3: CONSERVADOR | C3: PAPEL | D3: 0.3
A4: CONSERVADOR-TIJOLO | B4: CONSERVADOR | C4: TIJOLO | D4: 0.5
A5: CONSERVADOR-HIBRIDOS | B5: CONSERVADOR | C5: HIBRIDOS | D5: 0.1
A6: CONSERVADOR-FOPS | B6: CONSERVADOR | C6: FOPS | D6: 0.1
A7: CONSERVADOR-DESENVOLVIMENTO | B7: CONSERVADOR | C7: DESENVOLVIMENTO | D7: 0
A8: CONSERVADOR-HOTELARIAS | B8: CONSERVADOR | C8: HOTELARIAS | D8: 0
A9: MODERADO-PAPEL | B9: MODERADO | C9: PAPEL | D9: 0.32
A10: MODERADO-TIJOLO | B10: MODERADO | C10: TIJOLO | D10: 0.35
A11: MODERADO-HIBRIDOS | B11: MODERADO | C11: HIBRIDOS | D11: 0.08
A12: MODERADO-FOPS | B12: MODERADO | C12: FOPS | D12: 0.05
A13: MODERADO-DESENVOLVIMENTO | B13: MODERADO | C13: DESENVOLVIMENTO | D13: 0.1
A14: MODERADO-HOTELARIAS | B14: MODERADO | C14: HOTELARIAS | D14: 0.1
... A20: AGRESSIVO-HOTELARIAS | B20: AGRESSIVO | C20: HOTELARIAS | D20: 0.1
